hello.py
zeval_py-0.0.1.dist-info/METADATA
zeval_py-0.0.1.dist-info/WHEEL
zeval_py-0.0.1.dist-info/top_level.txt
zeval_py-0.0.1.dist-info/RECORD
